README
setup.py
django_harness.egg-info/PKG-INFO
django_harness.egg-info/SOURCES.txt
django_harness.egg-info/dependency_links.txt
django_harness.egg-info/top_level.txt
harness/__init__.py
harness/middleware.py
harness/settings_wrapper.py
harness/signals.py
harness/urls.py